Workbook

Sheet Inputs
A1: Core Inputs
A3: Ticker | B3: SNDK
A4: Shares Outstanding (mm)
A5: Current Price
A6: Net Debt (mm)
A7: Tax Rate | B7: 0.21
A8: WACC | B8: 0.1
A9: Terminal Growth | B9: 0.03

Sheet Historical
A2: Line Item | B2: FY2025 | C2: FY2024 | D2: FY2023
A3: Revenue | B3: 7355 | C3: 6663 | D3: 6086
A4: Gross Profit | B4: 2212 | C4: 1072 | D4: 430
A5: Operating Income | B5: -1377 | C5: -468 | D5: -2035
A6: Net Income | B6: -1641 | C6: -672 | D6: -2143

Sheet DCF_Model
A2: Metric | B2: 2026E | C2: 2027E | D2: 2028E | E2: 2029E | F2: 2030E
A3: Revenue | B3: 10666 | C3: =B3*(1+C4) | D3: =C3*(1+D4) | E3: =D3*(1+E4) | F3: =E3*(1+F4)
A4: Revenue Growth | B4: 0.05 | C4: 0.05 | D4: 0.05 | E4: 0.05 | F4: 0.05
A5: EBIT Margin | B5: 0.18 | C5: 0.18 | D5: 0.18 | E5: 0.18 | F5: 0.18
A6: EBIT | B6: =B3*B5 | C6: =C3*C5 | D6: =D3*D5 | E6: =E3*E5 | F6: =F3*F5
A7: Tax | B7: =-B6*Inputs!B7 | C7: =-C6*Inputs!B7 | D7: =-D6*Inputs!B7 | E7: =-E6*Inputs!B7 | F7: =-F6*Inputs!B7
A8: NOPAT | B8: =B6+B7 | C8: =C6+C7 | D8: =D6+D7 | E8: =E6+E7 | F8: =F6+F7
A9: Capex (% Rev) | B9: =-B3*B8 | C9: =-C3*C8 | D9: =-D3*D8 | E9: =-E3*E8 | F9: =-F3*F8
A10: Capex | B10: =B8+B9 | C10: =C8+C9 | D10: =D8+D9 | E10: =E8+E9 | F10: =F8+F9
A11: FCF | B11: =1/(1+Inputs!B6)^1 | C11: =1/(1+Inputs!B6)^2 | D11: =1/(1+Inputs!B6)^3 | E11: =1/(1+Inputs!B6)^4 | F11: =1/(1+Inputs!B6)^5
A12: Discount Factor | B12: =B10*B11 | C12: =C10*C11 | D12: =D10*D11 | E12: =E10*E11 | F12: =F10*F11
A13: PV of FCF
A14: Terminal Value
A15: TV | B15: =(F10*(1+Inputs!B8))/(Inputs!B6-Inputs!B8)
A16: PV of TV | B16: =B15*F11
A17: Enterprise Value | B17: =SUM(B12:F12)+B16
A18: Equity Value | B18: =B17-Inputs!B5
A19: Value Per Share | B19: =IFERROR(B18/Inputs!B3,"")

Sheet Comps
A2: Company | B2: Revenue | C2: EBITDA | D2: EV | E2: EV/EBITDA | F2: EV/Revenue
A3: Micron
A4: SK Hynix
A5: Samsung Memory

Sheet sPEG_Valuation
A2: Metric | B2: Value
A3: Forward P/E
A4: Forward EPS Growth %
A5: Scarcity Multiplier (1-3)
A6: sPEG Ratio | B6: =IFERROR(B3/B4*B5,"")

Sheet Scenarios
A2: Scenario | B2: Revenue Growth | C2: EBIT Margin | D2: WACC | E2: Implied Value/Share
A3: Base | B3: 0.05 | C3: 0.18 | D3: 0.1 | E3: =DCF_Model!B19
A4: Bull | B4: 0.08 | C4: 0.24 | D4: 0.09 | E4: =DCF_Model!B19
A5: Bear | B5: 0.02 | C5: 0.12 | D5: 0.11 | E5: =DCF_Model!B19

Sheet Cycle_Normalization
A2: Metric | B2: Value
A3: Peak EBIT Margin
A4: Mid-Cycle EBIT Margin
A5: Trough EBIT Margin
A6: Normalized EBIT (Revenue × Mid-Cycle Margin) | B6: =DCF_Model!B3*B4

Sheet Return_Waterfall
A2: Component | B2: Value
A3: Current Price | B3: =Inputs!B3
A4: Implied Value (Base) | B4: =DCF_Model!B19
A5: Upside / (Downside) | B5: =IFERROR(B4-B3,"")
A6: % Return | B6: =IFERROR((B4-B3)/B3,"")
