Workbook

Sheet Inputs
A1: Capital Allocator Inputs
A3: Shares Outstanding (mm)
A4: Current Price
A5: Net Debt (mm)
A6: Tax Rate | B6: 0.21
A7: WACC | B7: 0.1
A8: Terminal Growth | B8: 0.03
A9: Base Revenue (Annualized 6M) | B9: 10666

Sheet Cycle_Toggle
A2: Scenario | B2: Growth | C2: EBIT Margin | E2: Selected Scenario Row (3-5)
A3: Trough | B3: 0.02 | C3: 0.12 | E3: 4
A4: Mid-Cycle | B4: 0.05 | C4: 0.18
A5: Peak | B5: 0.08 | C5: 0.25

Sheet Allocator_DCF
A2: Metric | B2: Y1 | C2: Y2 | D2: Y3 | E2: Y4 | F2: Y5
A3: Revenue | B3: =Inputs!B9 | C3: =B3*(1+C4) | D3: =C3*(1+D4) | E3: =D3*(1+E4) | F3: =E3*(1+F4)
A4: Growth | B4: =INDEX(Cycle_Toggle!B3:B5,Cycle_Toggle!E3-2) | C4: =INDEX(Cycle_Toggle!B3:B5,Cycle_Toggle!E3-2) | D4: =INDEX(Cycle_Toggle!B3:B5,Cycle_Toggle!E3-2) | E4: =INDEX(Cycle_Toggle!B3:B5,Cycle_Toggle!E3-2) | F4: =INDEX(Cycle_Toggle!B3:B5,Cycle_Toggle!E3-2)
A5: EBIT Margin | B5: =INDEX(Cycle_Toggle!C3:C5,Cycle_Toggle!E3-2) | C5: =INDEX(Cycle_Toggle!C3:C5,Cycle_Toggle!E3-2) | D5: =INDEX(Cycle_Toggle!C3:C5,Cycle_Toggle!E3-2) | E5: =INDEX(Cycle_Toggle!C3:C5,Cycle_Toggle!E3-2) | F5: =INDEX(Cycle_Toggle!C3:C5,Cycle_Toggle!E3-2)
A6: EBIT | B6: =B3*B5 | C6: =C3*C5 | D6: =D3*D5 | E6: =E3*E5 | F6: =F3*F5
A7: Tax | B7: =-B6*Inputs!B6 | C7: =-C6*Inputs!B6 | D7: =-D6*Inputs!B6 | E7: =-E6*Inputs!B6 | F7: =-F6*Inputs!B6
A8: NOPAT | B8: =B6+B7 | C8: =C6+C7 | D8: =D6+D7 | E8: =E6+E7 | F8: =F6+F7
A9: FCF | B9: =B8 | C9: =C8 | D9: =D8 | E9: =E8 | F9: =F8
A10: Discount Factor | B10: =1/(1+Inputs!B7)^1 | C10: =1/(1+Inputs!B7)^2 | D10: =1/(1+Inputs!B7)^3 | E10: =1/(1+Inputs!B7)^4 | F10: =1/(1+Inputs!B7)^5
A11: PV FCF | B11: =B9*B10 | C11: =C9*C10 | D11: =D9*D10 | E11: =E9*E10 | F11: =F9*F10
A13: Terminal Value | B13: =(F9*(1+Inputs!B8))/(Inputs!B7-Inputs!B8)
A14: PV Terminal | B14: =B13*F10
A15: Enterprise Value | B15: =SUM(B11:F11)+B14
A16: Equity Value | B16: =B15-Inputs!B5
A17: Value Per Share | B17: =IFERROR(B16/Inputs!B3,"")

Sheet Comps_Engine
A2: Company | B2: EBITDA | C2: EV | D2: EV/EBITDA | E2: Implied EV | F2: Implied Price
A3: Micron | D3: =IFERROR(C3/B3,"") | E3: =D3*Allocator_DCF!F6 | F3: =IFERROR((E3-Inputs!B5)/Inputs!B3,"")
A4: SK Hynix | D4: =IFERROR(C4/B4,"") | E4: =D4*Allocator_DCF!F6 | F4: =IFERROR((E4-Inputs!B5)/Inputs!B3,"")
A5: Samsung Memory | D5: =IFERROR(C5/B5,"") | E5: =D5*Allocator_DCF!F6 | F5: =IFERROR((E5-Inputs!B5)/Inputs!B3,"")

Sheet sPEG_Engine
A2: Metric | B2: Value
A3: Forward P/E
A4: Forward EPS Growth
A5: Scarcity Multiplier (1-3)
A6: sPEG Ratio | B6: =IFERROR(B3/B4*B5,"")
A7: Implied Fair P/E | B7: =B4*B6/B5
